django_searchable_dropdown-1.0.2.dist-info/licenses/LICENSE
recoveredperispirit/__init__.py
recoveredperispirit/django/__init__.py
recoveredperispirit/django/django_searchable_dropdown/__init__.py
recoveredperispirit/django/django_searchable_dropdown/apps.py
recoveredperispirit/django/django_searchable_dropdown/create_test_data.py
recoveredperispirit/django/django_searchable_dropdown/forms.py
recoveredperispirit/django/django_searchable_dropdown/run_tests.py
recoveredperispirit/django/django_searchable_dropdown/utils.py
recoveredperispirit/django/django_searchable_dropdown/widgets.py
recoveredperispirit/django/django_searchable_dropdown/static/css/searchable-dropdown.css
recoveredperispirit/django/django_searchable_dropdown/static/js/searchable-dropdown-init.js
recoveredperispirit/django/django_searchable_dropdown/static/js/searchable-dropdown.js
recoveredperispirit/django/django_searchable_dropdown/templates/django_searchable_dropdown/widget.html
recoveredperispirit/django/django_searchable_dropdown/templates/django_searchable_dropdown/widget_ajax.html
recoveredperispirit/django/django_searchable_dropdown/templates/django_searchable_dropdown/widget_multiple.html
recoveredperispirit/django/django_searchable_dropdown/templates/django_searchable_dropdown/widget_with_info.html
recoveredperispirit/django/django_searchable_dropdown/tests/__init__.py
recoveredperispirit/django/django_searchable_dropdown/tests/conftest.py
recoveredperispirit/django/django_searchable_dropdown/tests/test_forms.py
recoveredperispirit/django/django_searchable_dropdown/tests/test_integration.py
recoveredperispirit/django/django_searchable_dropdown/tests/test_models.py
recoveredperispirit/django/django_searchable_dropdown/tests/test_runner.py
recoveredperispirit/django/django_searchable_dropdown/tests/test_settings.py
recoveredperispirit/django/django_searchable_dropdown/tests/test_utils.py
recoveredperispirit/django/django_searchable_dropdown/tests/test_widgets.py
recoveredperispirit/django/django_searchable_dropdown/tests/urls.py
django_searchable_dropdown-1.0.2.dist-info/METADATA
django_searchable_dropdown-1.0.2.dist-info/WHEEL
django_searchable_dropdown-1.0.2.dist-info/top_level.txt
django_searchable_dropdown-1.0.2.dist-info/RECORD
