Metadata-Version: 2.4
Name: django_searchable_dropdown
Version: 1.0.2
Summary: Biblioteca Django para criar dropdowns pesquisáveis e customizáveis
Home-page: https://github.com/novaalvorada/django_searchable_dropdown
Author: Marcio Bernardes
Author-email: Marcio Bernardes <marciobernardes@live.com>
License: MIT
Project-URL: Homepage, https://github.com/novaalvorada/django_searchable_dropdown
Project-URL: Documentation, https://django_searchable_dropdown.readthedocs.io/
Project-URL: Repository, https://github.com/novaalvorada/django_searchable_dropdown
Project-URL: Issues, https://github.com/novaalvorada/django_searchable_dropdown/issues
Keywords: django,dropdown,searchable,select,widget,form,field
Classifier: Development Status :: 5 - Production/Stable
Classifier: Environment :: Web Environment
Classifier: Framework :: Django
Classifier: Framework :: Django :: 2.2
Classifier: Framework :: Django :: 3.0
Classifier: Framework :: Django :: 3.1
Classifier: Framework :: Django :: 3.2
Classifier: Framework :: Django :: 4.0
Classifier: Framework :: Django :: 4.1
Classifier: Framework :: Django :: 4.2
Classifier: Framework :: Django :: 5.0
Classifier: Intended Audience :: Developers
Classifier: License :: OSI Approved :: MIT License
Classifier: Operating System :: OS Independent
Classifier: Programming Language :: Python
Classifier: Programming Language :: Python :: 3
Classifier: Programming Language :: Python :: 3.7
Classifier: Programming Language :: Python :: 3.8
Classifier: Programming Language :: Python :: 3.9
Classifier: Programming Language :: Python :: 3.10
Classifier: Programming Language :: Python :: 3.11
Classifier: Programming Language :: Python :: 3.12
Classifier: Topic :: Internet :: WWW/HTTP
Classifier: Topic :: Internet :: WWW/HTTP :: Dynamic Content
Classifier: Topic :: Software Development :: Libraries :: Python Modules
Classifier: Topic :: Software Development :: User Interfaces
Requires-Python: >=3.7
License-File: LICENSE
Requires-Dist: django>=2.2
Dynamic: author
Dynamic: home-page
Dynamic: license-file
Dynamic: requires-python
